chromat/__init__.py
chromat/palettes.py
chromat/swatches.py
chromat-0.1.0.dist-info/COPYING
chromat-0.1.0.dist-info/METADATA
chromat-0.1.0.dist-info/WHEEL
chromat-0.1.0.dist-info/RECORD
